[{
	"Guid": "7e57a2a4-8f61-441b-a461-d61151b6141b",
	"ObjectId": "ObjectId 11",
	"Description": "Description 11",
	"Zzfld00002a": "Zzfld00002a 11",
	"Source": "Source 11",
	"CurrPhase": "CurrPhase 11",
	"Probability": "Probability 11",
	"StatUser": "StatUser 11",
	"Memo": "Memo 11",
	"ExpectEnd": "/Date(1400316226000)/",
	"Zzfld00001g": "/Date(1451205826000)/",
	"NetValueMan": 4242.93,
	"Currency": "Currency 11",
	"ZzprodLine": "ZzprodLine 11",
	"Partner": "Partner 11",
	"PartnerT": "PartnerT 11",
	"__metadata": {
		"uri": "ZOPP_HEADERSet(guid'60737ba4-f357-4989-848a-eca3578c7d5a')",
		"type": "ZSALE_ODATA_01_SRV.ZOPP_HEADER"
	}
}, {
	"Guid": "d13d6308-e634-4134-842a-e23eeb68079d",
	"ObjectId": "ObjectId 12",
	"Description": "Description 12",
	"Zzfld00002a": "Zzfld00002a 12",
	"Source": "Source 12",
	"CurrPhase": "CurrPhase 12",
	"Probability": "Probability 12",
	"StatUser": "StatUser 12",
	"Memo": "Memo 12",
	"ExpectEnd": "/Date(1251362626000)/",
	"Zzfld00001g": "/Date(1088757826000)/",
	"NetValueMan": 5612.43,
	"Currency": "Currency 12",
	"ZzprodLine": "ZzprodLine 12",
	"Partner": "Partner 12",
	"PartnerT": "PartnerT 12",
	"__metadata": {
		"uri": "ZOPP_HEADERSet(guid'a31a684a-fb44-416a-8c49-29d11385b0cd')",
		"type": "ZSALE_ODATA_01_SRV.ZOPP_HEADER"
	}
}, {
	"Guid": "a669e566-a6c8-4f5d-916d-54382d736d8f",
	"ObjectId": "ObjectId 13",
	"Description": "Description 13",
	"Zzfld00002a": "Zzfld00002a 13",
	"Source": "Source 13",
	"CurrPhase": "CurrPhase 13",
	"Probability": "Probability 13",
	"StatUser": "StatUser 13",
	"Memo": "Memo 13",
	"ExpectEnd": "/Date(1233132226000)/",
	"Zzfld00001g": "/Date(1237797826000)/",
	"NetValueMan": 3737.64,
	"Currency": "Currency 13",
	"ZzprodLine": "ZzprodLine 13",
	"Partner": "Partner 13",
	"PartnerT": "PartnerT 13",
	"__metadata": {
		"uri": "ZOPP_HEADERSet(guid'81e90480-352d-4200-b1b7-36744f7ba2f4')",
		"type": "ZSALE_ODATA_01_SRV.ZOPP_HEADER"
	}
}, {
	"Guid": "8101284a-5703-4e25-a167-149efb09a35f",
	"ObjectId": "ObjectId 14",
	"Description": "Description 14",
	"Zzfld00002a": "Zzfld00002a 14",
	"Source": "Source 14",
	"CurrPhase": "CurrPhase 14",
	"Probability": "Probability 14",
	"StatUser": "StatUser 14",
	"Memo": "Memo 14",
	"ExpectEnd": "/Date(951295426000)/",
	"Zzfld00001g": "/Date(1302252226000)/",
	"NetValueMan": 2333.68,
	"Currency": "Currency 14",
	"ZzprodLine": "ZzprodLine 14",
	"Partner": "Partner 14",
	"PartnerT": "PartnerT 14",
	"__metadata": {
		"uri": "ZOPP_HEADERSet(guid'936c5032-91bc-4d6f-aa3d-58470844825b')",
		"type": "ZSALE_ODATA_01_SRV.ZOPP_HEADER"
	}
}, {
	"Guid": "2fe37507-83e0-4b39-bb46-0aff2522eec7",
	"ObjectId": "ObjectId 15",
	"Description": "Description 15",
	"Zzfld00002a": "Zzfld00002a 15",
	"Source": "Source 15",
	"CurrPhase": "CurrPhase 15",
	"Probability": "Probability 15",
	"StatUser": "StatUser 15",
	"Memo": "Memo 15",
	"ExpectEnd": "/Date(1530175426000)/",
	"Zzfld00001g": "/Date(1080290626000)/",
	"NetValueMan": 7131.95,
	"Currency": "Currency 15",
	"ZzprodLine": "ZzprodLine 15",
	"Partner": "Partner 15",
	"PartnerT": "PartnerT 15",
	"__metadata": {
		"uri": "ZOPP_HEADERSet(guid'75c03d95-e36d-484b-b4c0-5289ad940a89')",
		"type": "ZSALE_ODATA_01_SRV.ZOPP_HEADER"
	}
}, {
	"Guid": "3a198311-3089-41c3-800b-04f008fe6f63",
	"ObjectId": "ObjectId 16",
	"Description": "Description 16",
	"Zzfld00002a": "Zzfld00002a 16",
	"Source": "Source 16",
	"CurrPhase": "CurrPhase 16",
	"Probability": "Probability 16",
	"StatUser": "StatUser 16",
	"Memo": "Memo 16",
	"ExpectEnd": "/Date(1479977026000)/",
	"Zzfld00001g": "/Date(1374309826000)/",
	"NetValueMan": 7207.34,
	"Currency": "Currency 16",
	"ZzprodLine": "ZzprodLine 16",
	"Partner": "Partner 16",
	"PartnerT": "PartnerT 16",
	"__metadata": {
		"uri": "ZOPP_HEADERSet(guid'77f61a90-cc12-4f85-be4d-28655481ff19')",
		"type": "ZSALE_ODATA_01_SRV.ZOPP_HEADER"
	}
}, {
	"Guid": "88147337-dcb3-44e5-a702-3efc872509b9",
	"ObjectId": "ObjectId 17",
	"Description": "Description 17",
	"Zzfld00002a": "Zzfld00002a 17",
	"Source": "Source 17",
	"CurrPhase": "CurrPhase 17",
	"Probability": "Probability 17",
	"StatUser": "StatUser 17",
	"Memo": "Memo 17",
	"ExpectEnd": "/Date(1063097026000)/",
	"Zzfld00001g": "/Date(1479804226000)/",
	"NetValueMan": 3583.27,
	"Currency": "Currency 17",
	"ZzprodLine": "ZzprodLine 17",
	"Partner": "Partner 17",
	"PartnerT": "PartnerT 17",
	"__metadata": {
		"uri": "ZOPP_HEADERSet(guid'3c6fc2fe-c380-49c6-ab31-6f12ca1ae6b9')",
		"type": "ZSALE_ODATA_01_SRV.ZOPP_HEADER"
	}
}, {
	"Guid": "d00870a7-321d-41e0-b34d-d3983f2bc05f",
	"ObjectId": "ObjectId 18",
	"Description": "Description 18",
	"Zzfld00002a": "Zzfld00002a 18",
	"Source": "Source 18",
	"CurrPhase": "CurrPhase 18",
	"Probability": "Probability 18",
	"StatUser": "StatUser 18",
	"Memo": "Memo 18",
	"ExpectEnd": "/Date(1521276226000)/",
	"Zzfld00001g": "/Date(1326098626000)/",
	"NetValueMan": 6514.24,
	"Currency": "Currency 18",
	"ZzprodLine": "ZzprodLine 18",
	"Partner": "Partner 18",
	"PartnerT": "PartnerT 18",
	"__metadata": {
		"uri": "ZOPP_HEADERSet(guid'0ef18619-597a-41f3-8996-3eb683319e65')",
		"type": "ZSALE_ODATA_01_SRV.ZOPP_HEADER"
	}
}, {
	"Guid": "b466faf7-f685-4775-9580-3e9b71f0b92d",
	"ObjectId": "ObjectId 19",
	"Description": "Description 19",
	"Zzfld00002a": "Zzfld00002a 19",
	"Source": "Source 19",
	"CurrPhase": "CurrPhase 19",
	"Probability": "Probability 19",
	"StatUser": "StatUser 19",
	"Memo": "Memo 19",
	"ExpectEnd": "/Date(1202201026000)/",
	"Zzfld00001g": "/Date(1279701826000)/",
	"NetValueMan": 7343.79,
	"Currency": "Currency 19",
	"ZzprodLine": "ZzprodLine 19",
	"Partner": "Partner 19",
	"PartnerT": "PartnerT 19",
	"__metadata": {
		"uri": "ZOPP_HEADERSet(guid'63cb81a7-ca66-4526-948b-03d745fb4086')",
		"type": "ZSALE_ODATA_01_SRV.ZOPP_HEADER"
	}
}, {
	"Guid": "23d30869-cea0-49a8-a300-5e49462c8e76",
	"ObjectId": "ObjectId 20",
	"Description": "Description 20",
	"Zzfld00002a": "Zzfld00002a 20",
	"Source": "Source 20",
	"CurrPhase": "CurrPhase 20",
	"Probability": "Probability 20",
	"StatUser": "StatUser 20",
	"Memo": "Memo 20",
	"ExpectEnd": "/Date(1235983426000)/",
	"Zzfld00001g": "/Date(1071650626000)/",
	"NetValueMan": 8865.43,
	"Currency": "Currency 20",
	"ZzprodLine": "ZzprodLine 20",
	"Partner": "Partner 20",
	"PartnerT": "PartnerT 20",
	"__metadata": {
		"uri": "ZOPP_HEADERSet(guid'a5e6d8c8-c202-47e6-ad66-b91cba190cc2')",
		"type": "ZSALE_ODATA_01_SRV.ZOPP_HEADER"
	}
}]